PersonalAssistant/address.py
PersonalAssistant/addressbook.py
PersonalAssistant/birthday.py
PersonalAssistant/book_saver.py
PersonalAssistant/email.py
PersonalAssistant/field.py
PersonalAssistant/main.py
PersonalAssistant/messages.py
PersonalAssistant/murzilka.py
PersonalAssistant/name.py
PersonalAssistant/note.py
PersonalAssistant/notebook.py
PersonalAssistant/phone.py
PersonalAssistant/record.py
build/lib/PersonalAssistant/address.py
build/lib/PersonalAssistant/addressbook.py
build/lib/PersonalAssistant/birthday.py
build/lib/PersonalAssistant/book_saver.py
build/lib/PersonalAssistant/email.py
build/lib/PersonalAssistant/field.py
build/lib/PersonalAssistant/main.py
build/lib/PersonalAssistant/messages.py
build/lib/PersonalAssistant/murzilka.py
build/lib/PersonalAssistant/name.py
build/lib/PersonalAssistant/note.py
build/lib/PersonalAssistant/notebook.py
build/lib/PersonalAssistant/phone.py
build/lib/PersonalAssistant/record.py
build/lib/build/lib/PersonalAssistant/address.py
build/lib/build/lib/PersonalAssistant/addressbook.py
build/lib/build/lib/PersonalAssistant/birthday.py
build/lib/build/lib/PersonalAssistant/book_saver.py
build/lib/build/lib/PersonalAssistant/email.py
build/lib/build/lib/PersonalAssistant/field.py
build/lib/build/lib/PersonalAssistant/main.py
build/lib/build/lib/PersonalAssistant/messages.py
build/lib/build/lib/PersonalAssistant/murzilka.py
build/lib/build/lib/PersonalAssistant/name.py
build/lib/build/lib/PersonalAssistant/note.py
build/lib/build/lib/PersonalAssistant/notebook.py
build/lib/build/lib/PersonalAssistant/phone.py
build/lib/build/lib/PersonalAssistant/record.py
build/lib/build/lib/build/lib/PersonalAssistant/address.py
build/lib/build/lib/build/lib/PersonalAssistant/addressbook.py
build/lib/build/lib/build/lib/PersonalAssistant/birthday.py
build/lib/build/lib/build/lib/PersonalAssistant/book_saver.py
build/lib/build/lib/build/lib/PersonalAssistant/email.py
build/lib/build/lib/build/lib/PersonalAssistant/field.py
PerAssist-13.dist-info/METADATA
PerAssist-13.dist-info/WHEEL
PerAssist-13.dist-info/entry_points.txt
PerAssist-13.dist-info/top_level.txt
PerAssist-13.dist-info/RECORD
